{"sgc":false,"sfy":false,"qfy":false,"lyricUser":{"id":1301884692,"status":99,"demand":0,"userid":567754263,"nickname":"浅草丶纳凉","uptime":1566473450488},"lrc":{"version":20,"lyric":"[00:00.000] 作曲 : Bye\n[00:01.000] 作词 : Bye\n[00:21.95]编曲：Bye\n[00:23.58]混音：MR鱼\n[00:25.24]母带：MR曾经\n[00:27.09]封面：小草清清\n[00:38.07]烟雨入江南\n[00:40.33]山水如墨染\n[00:43.02]宛若丹青未干\n[00:44.93]提笔然 点欲穿\n[00:48.59]行舟临秀川\n[00:50.89]画鷁推清澜\n[00:54.06]缱绻怡然\n[00:58.96]天色沉靛蓝\n[01:01.64]波光似锦缎\n[01:04.31]缀着零星白帆\n[01:06.79]诗情满 千卷难\n[01:09.79]渔舟齐桅杆\n[01:12.36]鸳鸯凭舷栏\n[01:15.37]琴瑟相伴\n[01:21.05]一叶轻船\n[01:23.41]一双桨悠懒\n[01:26.28]一绵江风微拂素罗衫\n[01:31.95]渔火点点聚散\n[01:34.38]欸乃声声浅淡\n[01:37.14]天近晚\n[01:38.74]炊烟袅飘沿斑\n[01:42.41]一叶轻船\n[01:44.73]一双人倚揽\n[01:47.70]一曲烟雨行舟太缓慢\n[01:53.16]执手相看\n[01:55.59]把酒当歌言欢\n[01:58.73]红尘路漫漫\n[02:02.05]愿今生与你共览\n[02:51.49]暮霭渐褪暗\n[02:53.70]胭脂余味淡\n[02:56.30]我支着竹绢伞\n[02:58.75]你闲摆花团扇\n[03:01.82]浪儿晃曳慢\n[03:04.30]夜垂云流缓\n[03:07.54]且吟且谈\n[03:13.08]一叶轻船\n[03:15.52]一双桨悠懒\n[03:18.40]一绵江风微拂素罗衫\n[03:23.88]渔火点点聚散\n[03:26.38]欸乃声声浅淡\n[03:29.10]天近晚\n[03:30.79]炊烟袅飘沿斑\n[03:34.57]一叶轻船\n[03:36.78]一双人倚揽\n[03:39.69]一曲烟雨行舟太缓慢\n[03:45.01]执手相看\n[03:47.48]把酒当歌言欢\n[03:50.72]红尘路漫漫\n[03:54.18]欲今生与你共览\n[03:57.64]一叶轻船\n[03:58.32]一双月对半\n[04:01.13]一帘清梦幽幽醉阑珊\n[04:06.21]移舟靠岸\n[04:09.10]案前惟剩空盏\n[04:12.14]莫怨良辰短\n[04:15.47]曲终了韵意未完\n[04:20.47]*第一次制作，感谢支持。\n"},"tlyric":{"version":0,"lyric":null},"code":200}